{
  "id": "flutter-easy-refresh-MGrO8h",
  "type": "repo",
  "name": "flutter_easy_refresh",
  "nameEn": "flutter_easy_refresh",
  "url": "https://github.com/xuelongqy/flutter_easy_refresh",
  "homepage": "https://xuelongqy.github.io/flutter_easy_refresh/",
  "summary": "下拉刷新以及上拉加载\n在线预览地址：https://xuelongqy.github.io/flutter_easy_refresh/",
  "description": "",
  "notes": "",
  "images": [
    "/assets/images/flutter-easy-refresh-MGrO8h/1.jpg"
  ],
  "thumbnail": "/assets/images/flutter-easy-refresh-MGrO8h/thumb.jpg",
  "category": "flutter",
  "tags": [
    "下拉刷新"
  ],
  "github": {
    "stars": 4052,
    "forks": 666,
    "language": "Dart",
    "license": "MIT",
    "lastUpdate": "2026-02-06",
    "topics": [
      "easy-refresh",
      "flutter",
      "load-more",
      "refresh"
    ],
    "createdAt": "2018-11-28"
  },
  "archived": false,
  "createdAt": "2026-01-22",
  "updatedAt": "2026-02-10T06:59:51.861Z"
}