{
  "id": "halo-sC-OnM",
  "type": "repo",
  "name": "halo",
  "nameEn": "halo",
  "url": "https://github.com/halo-dev/halo",
  "homepage": "https://www.halo.run",
  "summary": "强大易用的开源建站工具。\nhttps://www.halo.run/",
  "description": "",
  "notes": "",
  "images": [
    "/assets/images/halo-sC-OnM/1.jpg"
  ],
  "thumbnail": "/assets/images/halo-sC-OnM/thumb.jpg",
  "category": "frontend",
  "tags": [
    "建站",
    "博客"
  ],
  "github": {
    "stars": 37865,
    "forks": 10193,
    "language": "Java",
    "license": "GPL-3.0",
    "lastUpdate": "2026-01-23",
    "topics": [
      "blog",
      "blog-engine",
      "cms",
      "content-management-system",
      "halo",
      "halocms",
      "website-builder"
    ],
    "createdAt": "2018-03-21"
  },
  "archived": false,
  "createdAt": "2026-01-23",
  "updatedAt": "2026-01-23"
}