{
  "id": "sqlite-swift-kQfM_E",
  "type": "repo",
  "name": "SQLite.swift",
  "nameEn": "SQLite.swift",
  "url": "https://github.com/stephencelis/SQLite.swift",
  "summary": "A type-safe, Swift-language layer over SQLite3.",
  "description": "",
  "notes": "",
  "images": [
    "/assets/images/sqlite-swift-kQfM_E/1.jpg"
  ],
  "thumbnail": "/assets/images/sqlite-swift-kQfM_E/thumb.jpg",
  "category": "iOS",
  "tags": [
    "sqlite",
    "swift"
  ],
  "github": {
    "stars": 10086,
    "forks": 1626,
    "language": "Swift",
    "license": "MIT",
    "lastUpdate": "2026-01-23",
    "topics": [
      "sqlite",
      "swift"
    ],
    "createdAt": "2014-10-04"
  },
  "archived": false,
  "createdAt": "2026-01-24",
  "updatedAt": "2026-01-24"
}